[{"name": "Mount Everest", "height": 8850, "lat": 27.988055555, "lon": 86.925, "country": "Nepal, People's Republic of China"}, {"name": "Tohil Mons", "height": 8800, "lat": -28.42, "lon": 161.57, "country": ""}, {"name": "K2", "height": 8611, "lat": 35.881111111, "lon": 76.513333333, "country": "Pakistan"}, {"name": "Mongibello Mons", "height": 8600, "lat": 22.67, "lon": 67.05, "country": ""}, {"name": "Kanchenjunga", "height": 8586, "lat": 27.7, "lon": 88.133333, "country": "Nepal, India"}, {"name": "Lhotse", "height": 8516, "lat": 27.961666666, "lon": 86.933333333, "country": "Nepal, People's Republic of China"}]